postbp/__init__.py
postbp/common.py
postbp/dailyfirevectors.py
postbp/dataloader.py
postbp/finalfirevectors.py
postbp/postbp.py
postbp/spreadrose.py
postbp/tessellation.py
postbp-1.2.1.dist-info/LICENSE
postbp-1.2.1.dist-info/METADATA
postbp-1.2.1.dist-info/WHEEL
postbp-1.2.1.dist-info/entry_points.txt
postbp-1.2.1.dist-info/top_level.txt
postbp-1.2.1.dist-info/RECORD
