Metadata-Version: 2.1
Name: postbp
Version: 1.2.1
Summary: A Python Library
Author-email: Ning Liu <ning.liu@nrcan-rncan.gc.ca>
License: MIT License
Project-URL: Homepage, https://github.com/nliu-cfs/postbp
Keywords: postbp
Classifier: Intended Audience :: Developers
Classifier: License :: OSI Approved :: MIT License
Classifier: Natural Language :: English
Classifier: Programming Language :: Python :: 3.8
Classifier: Programming Language :: Python :: 3.9
Classifier: Programming Language :: Python :: 3.10
Classifier: Programming Language :: Python :: 3.11
Classifier: Programming Language :: Python :: 3.12
Requires-Python: >=3.8
License-File: LICENSE
Requires-Dist: numpy
Requires-Dist: pandas
Requires-Dist: geopandas
Requires-Dist: shapely
Requires-Dist: windrose
Requires-Dist: matplotlib
Requires-Dist: tqdm
Provides-Extra: all
Requires-Dist: postbp[extra]; extra == "all"
Provides-Extra: extra
Requires-Dist: pandas; extra == "extra"
